LICENSE
MANIFEST.in
README.rst
setup.cfg
setup.py
py_heat.egg-info/PKG-INFO
py_heat.egg-info/SOURCES.txt
py_heat.egg-info/dependency_links.txt
py_heat.egg-info/entry_points.txt
py_heat.egg-info/requires.txt
py_heat.egg-info/top_level.txt
pyheat/__init__.py
pyheat/commandline.py
pyheat/pyheat.py