Metadata-Version: 1.1
Name: py-heat
Version: 0.0.2
Summary: pprofile + matplotlib = Python program profiled as an awesome heatmap!
Home-page: https://github.com/csurfer/pyheat
Author: Vishwas B Sharma
Author-email: sharma.vishwas88@gmail.com
License: MIT
Keywords: heatmap matplotlib profiling python
Platform: UNKNOWN
Classifier: Intended Audience :: Developers
Classifier: Intended Audience :: Education
Classifier: License :: OSI Approved :: MIT License
Classifier: Development Status :: 3 - Alpha
Classifier: Operating System :: POSIX
Classifier: Programming Language :: Python :: 2.7
Classifier: Programming Language :: Python :: 3.4
Classifier: Programming Language :: Python :: 3.5
Classifier: Programming Language :: Python :: 3.6
Classifier: Topic :: Software Development :: Build Tools
Classifier: Topic :: Software Development :: Libraries :: Python Modules
